tests/__init__.py
tests/models.py
tests/settings.py
tests/test_admin.py
tests/test_frontend.py
tests/test_models.py
tests/urls.py
tests/migrations/0001_initial.py
tests/migrations/__init__.py
wagtail_review/__init__.py
wagtail_review/admin_urls.py
wagtail_review/apps.py
wagtail_review/forms.py
wagtail_review/models.py
wagtail_review/text.py
wagtail_review/urls.py
wagtail_review/wagtail_hooks.py
wagtail_review/migrations/0001_initial.py
wagtail_review/migrations/0002_annotation_annotationrange.py
wagtail_review/migrations/0003_response.py
wagtail_review/migrations/__init__.py
wagtail_review/static/wagtail_review/css/annotator.css
wagtail_review/static/wagtail_review/css/audit_trail.css
wagtail_review/static/wagtail_review/css/create_review.css
wagtail_review/static/wagtail_review/css/respond.css
wagtail_review/static/wagtail_review/js/annotator-2.0.0a3.min.js
wagtail_review/static/wagtail_review/js/annotator-extensions.js
wagtail_review/static/wagtail_review/js/submit.js
wagtail_review/templates/wagtail_review/annotate.html
wagtail_review/templates/wagtail_review/create_review.html
wagtail_review/templates/wagtail_review/response_form_fields.html
wagtail_review/templates/wagtail_review/submit_for_review_menu_item.html
wagtail_review/templates/wagtail_review/admin/audit_trail.html
wagtail_review/templates/wagtail_review/admin/dashboard.html
wagtail_review/templates/wagtail_review/email/request_review.txt
wagtail_review/templates/wagtail_review/email/request_review_subject.txt
wagtail_review/templates/wagtail_review/email/response_received.txt
wagtail_review/templates/wagtail_review/email/response_received_subject.txt
wagtail_review/templatetags/__init__.py
wagtail_review/templatetags/wagtailreview_admin_tags.py
wagtail_review/templatetags/wagtailreview_tags.py
wagtail_review/views/__init__.py
wagtail_review/views/admin.py
wagtail_review/views/annotations_api.py
wagtail_review/views/frontend.py
wagtail_review-0.5.dist-info/LICENSE
wagtail_review-0.5.dist-info/METADATA
wagtail_review-0.5.dist-info/WHEEL
wagtail_review-0.5.dist-info/top_level.txt
wagtail_review-0.5.dist-info/RECORD
